destination_glassflow/__init__.py
destination_glassflow/destination.py
destination_glassflow/run.py
destination_glassflow/spec.json
airbyte_destination_glassflow-0.1.6.dist-info/METADATA
airbyte_destination_glassflow-0.1.6.dist-info/WHEEL
airbyte_destination_glassflow-0.1.6.dist-info/entry_points.txt
airbyte_destination_glassflow-0.1.6.dist-info/RECORD
