Metadata-Version: 2.3
Name: airbyte-destination-glassflow
Version: 0.1.6
Summary: Destination implementation for GlassFlow.
License: MIT
Author: Airbyte
Author-email: contact@airbyte.io
Requires-Python: >=3.10,<3.12
Classifier: License :: OSI Approved :: MIT License
Classifier: Programming Language :: Python :: 3
Classifier: Programming Language :: Python :: 3.10
Classifier: Programming Language :: Python :: 3.11
Requires-Dist: airbyte-cdk (>=4.6.2,<5.0.0)
Requires-Dist: glassflow (>=2.1.0)
Project-URL: Documentation, https://docs.airbyte.com/integrations/destinations/glassflow
Project-URL: Homepage, https://airbyte.com
Project-URL: Repository, https://github.com/airbytehq/airbyte
